{"ai-models.md":"DkV6GLGT","architecture.md":"UBtBwtcj","config.md":"BiPO8oVU","contributing.md":"DFiatpWd","faq.md":"C90aUf74","features.md":"DFoIxbRU","getting-started.md":"BQ5pvgsy","guide_ai-configuration.md":"BdOX2ucN","guide_ai-video-guide.md":"BhxWYyya","guide_batch-processing.md":"D3adKCvj","guide_exporting.md":"DAPxNrGm","guide_getting-started.md":"CYBK_Jb7","guide_installation.md":"ChFxnKid","guide_interface.md":"Cz02J4mW","guide_plugin-development.md":"DaNlG2rw","guide_quick-start.md":"DbkE52OI","guide_troubleshooting.md":"DdgSjPO3","index.md":"Ccin7JvJ","model-updates.md":"DBgSGEdB","readme.md":"BIrdLbFt","security.md":"BJGqzs3S","troubleshooting.md":"CLUcQF6k"}
