{"ai-models.md":"C7uGEfpd","architecture.md":"BuwgoRHF","config.md":"BT4LcA_P","contributing.md":"Bc-c6YWF","faq.md":"D_Zf0q7W","features.md":"Cmc4Rp-S","getting-started.md":"VYcfbqai","guide_ai-configuration.md":"Cb-mhUEK","guide_ai-video-guide.md":"1MCHXTvD","guide_batch-processing.md":"CyyocMd7","guide_exporting.md":"B3qf-m_r","guide_getting-started.md":"BJJkO0WC","guide_installation.md":"CVc5fyT8","guide_interface.md":"XKKDWJeh","guide_plugin-development.md":"CMwWojUl","guide_quick-start.md":"BZ3Hfw1g","guide_troubleshooting.md":"CYcdkhD8","index.md":"CdGXgEXi","model-updates.md":"Bw2wWVXN","readme.md":"BGSuFx3a","security.md":"CjijPTnF","troubleshooting.md":"CWjvZg9x"}
